odoo/addons/project_type/README.rst
odoo/addons/project_type/__init__.py
odoo/addons/project_type/__manifest__.py
odoo/addons/project_type/i18n/ca.po
odoo/addons/project_type/i18n/de.po
odoo/addons/project_type/i18n/es.po
odoo/addons/project_type/i18n/es_AR.po
odoo/addons/project_type/i18n/fi.po
odoo/addons/project_type/i18n/fr.po
odoo/addons/project_type/i18n/fr_FR.po
odoo/addons/project_type/i18n/it.po
odoo/addons/project_type/i18n/nl.po
odoo/addons/project_type/i18n/project_type.pot
odoo/addons/project_type/i18n/pt.po
odoo/addons/project_type/i18n/pt_BR.po
odoo/addons/project_type/i18n/tr.po
odoo/addons/project_type/models/__init__.py
odoo/addons/project_type/models/project_project.py
odoo/addons/project_type/models/project_task.py
odoo/addons/project_type/models/project_type.py
odoo/addons/project_type/readme/CONTRIBUTORS.md
odoo/addons/project_type/readme/DESCRIPTION.md
odoo/addons/project_type/readme/USAGE.md
odoo/addons/project_type/security/ir.model.access.csv
odoo/addons/project_type/static/description/icon.png
odoo/addons/project_type/static/description/index.html
odoo/addons/project_type/tests/__init__.py
odoo/addons/project_type/tests/test_project_type.py
odoo/addons/project_type/views/project_project_views.xml
odoo/addons/project_type/views/project_task_views.xml
odoo/addons/project_type/views/project_type_views.xml
odoo_addon_project_type-18.0.1.0.0.8.dist-info/METADATA
odoo_addon_project_type-18.0.1.0.0.8.dist-info/WHEEL
odoo_addon_project_type-18.0.1.0.0.8.dist-info/top_level.txt
odoo_addon_project_type-18.0.1.0.0.8.dist-info/RECORD
