Metadata-Version: 2.1
Name: odoo-addon-project_type
Version: 18.0.1.0.0.8
Requires-Python: >=3.10
Requires-Dist: odoo==18.0.*
Summary: Project Types
Home-page: https://github.com/OCA/project
License: AGPL-3
Author: ADHOC SA,Tecnativa, Onestein, Odoo Community Association (OCA)
Author-email: support@odoo-community.org
Classifier: Programming Language :: Python
Classifier: Framework :: Odoo
Classifier: Framework :: Odoo :: 18.0
Classifier: License :: OSI Approved :: GNU Affero General Public License v3
